Metadata-Version: 2.1
Name: tg-log-handler
Version: 0.0.1
Summary: Async Telegram Logging Handler
Home-page: https://lolz.guru/members/2977610/
Author: zcxw
License: UNKNOWN
Platform: UNKNOWN
